[
  {
    "name": "id",
    "dbType": "increments",
    "fillable": false,
    "primary": true,
    "inForm": false,
    "inIndex": false
  },
  {
    "name": "email",
    "dbType": "string:unique",
    "htmlType": "text",
    "validations": "required",
    "searchable": true
  },
  {
    "name": "name",
    "dbType": "string",
    "htmlType": "text",
    "searchable": true
  },
  {
    "name": "created_at",
    "dbType": "timestamp",
    "htmlType": "",
    "validations": "",
    "searchable": false,
    "fillable": false,
    "primary": false,
    "inForm": false,
    "inIndex": false
  },
  {
    "name": "updated_at",
    "dbType": "timestamp",
    "htmlType": "",
    "validations": "",
    "searchable": false,
    "fillable": false,
    "primary": false,
    "inForm": false,
    "inIndex": false
  }
]